[
	{
		"pkg": "@capacitor-community/apple-sign-in",
		"classpath": "com.getcapacitor.community.applesignin.SignInWithApple"
	},
	{
		"pkg": "@capacitor-community/speech-recognition",
		"classpath": "com.getcapacitor.community.speechrecognition.SpeechRecognition"
	},
	{
		"pkg": "@capacitor/app",
		"classpath": "com.capacitorjs.plugins.app.AppPlugin"
	},
	{
		"pkg": "@capacitor/browser",
		"classpath": "com.capacitorjs.plugins.browser.BrowserPlugin"
	},
	{
		"pkg": "@capacitor/haptics",
		"classpath": "com.capacitorjs.plugins.haptics.HapticsPlugin"
	},
	{
		"pkg": "@ebarooni/capacitor-calendar",
		"classpath": "dev.barooni.capacitor.calendar.CapacitorCalendarPlugin"
	},
	{
		"pkg": "@revenuecat/purchases-capacitor",
		"classpath": "com.revenuecat.purchases.capacitor.PurchasesPlugin"
	}
]
